postman_runner/__init__.py
postman_runner/assertions.py
postman_runner/cli.py
postman_runner/collection_parser.py
postman_runner/environment.py
postman_runner/executor.py
postman_runner/models.py
postman_runner/test_runner.py
postman_runner-0.2.0.dist-info/METADATA
postman_runner-0.2.0.dist-info/WHEEL
postman_runner-0.2.0.dist-info/entry_points.txt
postman_runner-0.2.0.dist-info/top_level.txt
postman_runner-0.2.0.dist-info/RECORD
